sphinxcontrib_autodoc_doxygen-0.7.0-py3.9-nspkg.pth
sphinxcontrib/autodoc_doxygen/__init__.py
sphinxcontrib/autodoc_doxygen/autodoc.py
sphinxcontrib/autodoc_doxygen/xmlutils.py
sphinxcontrib/autodoc_doxygen/autosummary/__init__.py
sphinxcontrib/autodoc_doxygen/autosummary/generate.py
sphinxcontrib/autodoc_doxygen/autosummary/templates/doxyclass.rst
sphinxcontrib_autodoc_doxygen-0.7.0.dist-info/AUTHORS
sphinxcontrib_autodoc_doxygen-0.7.0.dist-info/LICENSE
sphinxcontrib_autodoc_doxygen-0.7.0.dist-info/METADATA
sphinxcontrib_autodoc_doxygen-0.7.0.dist-info/WHEEL
sphinxcontrib_autodoc_doxygen-0.7.0.dist-info/namespace_packages.txt
sphinxcontrib_autodoc_doxygen-0.7.0.dist-info/pbr.json
sphinxcontrib_autodoc_doxygen-0.7.0.dist-info/top_level.txt
sphinxcontrib_autodoc_doxygen-0.7.0.dist-info/RECORD
