Metadata-Version: 2.1
Name: sphinxcontrib-autodoc-doxygen
Version: 0.7.0
Summary: Doxygen / Sphinx bridge, with autodoc and autosummary
Home-page: https://github.com/rmcgibbo/sphinxcontrib-autodoc_doxygen
Author: Robert T. McGibbon
Author-email: rmcgibbo@gmail.com
License: MIT
Keywords: sphinx,doxygen
Platform: any
Classifier: Development Status :: 3 - Alpha
Classifier: Environment :: Console
Classifier: Environment :: Web Environment
Classifier: Intended Audience :: Developers
Classifier: License :: OSI Approved :: MIT License
Classifier: Operating System :: OS Independent
Classifier: Programming Language :: Python
Classifier: Programming Language :: Python :: 2
Classifier: Programming Language :: Python :: 2.7
Classifier: Programming Language :: Python :: 3
Classifier: Programming Language :: Python :: 3.3
Classifier: Programming Language :: Python :: 3.4
Classifier: Programming Language :: Python :: Implementation :: CPython
Classifier: Programming Language :: Python :: Implementation :: PyPy
Classifier: Topic :: Documentation
Classifier: Topic :: Utilities
Requires-Dist: Sphinx (>=2.0)
Requires-Dist: docutils (>=0.11)
Requires-Dist: Jinja2 (>=2.3)
Requires-Dist: lxml
Requires-Dist: mock
